bootstrap_9add/__init__.py
bootstrap_9add/__main__.py
bootstrap_9add/impl.py
bootstrap_9add-0.0.8.dist-info/LICENSE.txt
bootstrap_9add-0.0.8.dist-info/METADATA
bootstrap_9add-0.0.8.dist-info/WHEEL
bootstrap_9add-0.0.8.dist-info/entry_points.txt
bootstrap_9add-0.0.8.dist-info/top_level.txt
bootstrap_9add-0.0.8.dist-info/RECORD
