Metadata-Version: 2.1
Name: bootstrap-9add
Version: 0.0.8
Summary: A small example package
Home-page: https://github.com/phfrohring/python
Author: Pierre-Henry Fröhring
Author-email: contact@phfrohring.com
License: UNKNOWN
Project-URL: Bug Tracker, https://github.com/phfrohring/python/issues
Platform: UNKNOWN
Classifier: Programming Language :: Python :: 3
Classifier: License :: OSI Approved :: Mozilla Public License 2.0 (MPL 2.0)
Classifier: Operating System :: OS Independent
Requires-Python: >=3.8
Requires-Dist: program-9ef5
